{
  "ATG": [
    "XCD"
  ],
  "BTN": [
    "BTN",
    "INR"
  ],
  "ITA": [
    "EUR"
  ],
  "TUV": [
    "AUD",
    "TVD"
  ],
  "AIA": [
    "XCD"
  ],
  "AUS": [
    "AUD"
  ],
  "BLZ": [
    "BZD"
  ],
  "VUT": [
    "VUV"
  ],
  "BLR": [
    "BYN"
  ],
  "MUS": [
    "MUR"
  ],
  "LAO": [
    "LAK"
  ],
  "SEN": [
    "XOF"
  ],
  "TUR": [
    "TRY"
  ],
  "BOL": [
    "BOB"
  ],
  "LKA": [
    "LKR"
  ],
  "NFK": [
    "AUD"
  ],
  "CHN": [
    "CNY"
  ],
  "BES": [
    "USD"
  ],
  "GGY": [
    "GBP",
    "GGP"
  ],
  "SDN": [
    "SDG"
  ],
  "MYT": [
    "EUR"
  ],
  "BLM": [
    "EUR"
  ],
  "VAT": [
    "EUR"
  ],
  "TCA": [
    "USD"
  ],
  "CUW": [
    "ANG"
  ],
  "BWA": [
    "BWP"
  ],
  "BEN": [
    "XOF"
  ],
  "LTU": [
    "EUR"
  ],
  "MSR": [
    "XCD"
  ],
  "VGB": [
    "USD"
  ],
  "BDI": [
    "BIF"
  ],
  "UMI": [
    "USD"
  ],
  "IRL": [
    "EUR"
  ],
  "SLB": [
    "SBD"
  ],
  "BMU": [
    "BMD"
  ],
  "FIN": [
    "EUR"
  ],
  "PER": [
    "PEN"
  ],
  "BGD": [
    "BDT"
  ],
  "DNK": [
    "DKK"
  ],
  "VCT": [
    "XCD"
  ],
  "DOM": [
    "DOP"
  ],
  "MDA": [
    "MDL"
  ],
  "BGR": [
    "BGN"
  ],
  "CRI": [
    "CRC"
  ],
  "NAM": [
    "NAD",
    "ZAR"
  ],
  "SJM": [
    "NOK"
  ],
  "LUX": [
    "EUR"
  ],
  "RUS": [
    "RUB"
  ],
  "ARE": [
    "AED"
  ],
  "SXM": [
    "ANG"
  ],
  "BHS": [
    "BSD",
    "USD"
  ],
  "JPN": [
    "JPY"
  ],
  "NGA": [
    "NGN"
  ],
  "GHA": [
    "GHS"
  ],
  "SLE": [
    "SLE"
  ],
  "SPM": [
    "EUR"
  ],
  "ALB": [
    "ALL"
  ],
  "TKL": [
    "NZD"
  ],
  "SHN": [
    "GBP",
    "SHP"
  ],
  "TON": [
    "TOP"
  ],
  "TKM": [
    "TMT"
  ],
  "DJI": [
    "DJF"
  ],
  "CAF": [
    "XAF"
  ],
  "LBN": [
    "LBP"
  ],
  "LVA": [
    "EUR"
  ],
  "CCK": [
    "AUD"
  ],
  "GMB": [
    "GMD"
  ],
  "HND": [
    "HNL"
  ],
  "NIU": [
    "NZD"
  ],
  "MRT": [
    "MRU"
  ],
  "UNK": [
    "EUR"
  ],
  "WLF": [
    "XPF"
  ],
  "SGS": [
    "GBP"
  ],
  "PYF": [
    "XPF"
  ],
  "TGO": [
    "XOF"
  ],
  "BEL": [
    "EUR"
  ],
  "ZMB": [
    "ZMW"
  ],
  "CYM": [
    "KYD"
  ],
  "PCN": [
    "NZD"
  ],
  "COK": [
    "CKD",
    "NZD"
  ],
  "MDG": [
    "MGA"
  ],
  "MNE": [
    "EUR"
  ],
  "KOR": [
    "KRW"
  ],
  "ETH": [
    "ETB"
  ],
  "MNG": [
    "MNT"
  ],
  "SVK": [
    "EUR"
  ],
  "CUB": [
    "CUC",
    "CUP"
  ],
  "GTM": [
    "GTQ"
  ],
  "GUF": [
    "EUR"
  ],
  "NOR": [
    "NOK"
  ],
  "GRD": [
    "XCD"
  ],
  "REU": [
    "EUR"
  ],
  "CHL": [
    "CLP"
  ],
  "COL": [
    "COP"
  ],
  "SAU": [
    "SAR"
  ],
  "ISR": [
    "ILS"
  ],
  "DEU": [
    "EUR"
  ],
  "NZL": [
    "NZD"
  ],
  "GRL": [
    "DKK"
  ],
  "KGZ": [
    "KGS"
  ],
  "SLV": [
    "USD"
  ],
  "FRO": [
    "DKK",
    "FOK"
  ],
  "PLW": [
    "USD"
  ],
  "MLT": [
    "EUR"
  ],
  "SYR": [
    "SYP"
  ],
  "TLS": [
    "USD"
  ],
  "HRV": [
    "EUR"
  ],
  "PNG": [
    "PGK"
  ],
  "NLD": [
    "EUR"
  ],
  "LBR": [
    "LRD"
  ],
  "SOM": [
    "SOS"
  ],
  "VEN": [
    "VES"
  ],
  "HTI": [
    "HTG"
  ],
  "DZA": [
    "DZD"
  ],
  "MNP": [
    "USD"
  ],
  "MAF": [
    "EUR"
  ],
  "ABW": [
    "AWG"
  ],
  "EGY": [
    "EGP"
  ],
  "MWI": [
    "MWK"
  ],
  "GNQ": [
    "XAF"
  ],
  "VIR": [
    "USD"
  ],
  "ECU": [
    "USD"
  ],
  "UZB": [
    "UZS"
  ],
  "GAB": [
    "XAF"
  ],
  "SSD": [
    "SSP"
  ],
  "IRN": [
    "IRR"
  ],
  "KAZ": [
    "KZT"
  ],
  "NIC": [
    "NIO"
  ],
  "ISL": [
    "ISK"
  ],
  "SVN": [
    "EUR"
  ],
  "GLP": [
    "EUR"
  ],
  "CMR": [
    "XAF"
  ],
  "ARG": [
    "ARS"
  ],
  "AZE": [
    "AZN"
  ],
  "UGA": [
    "UGX"
  ],
  "NER": [
    "XOF"
  ],
  "CXR": [
    "AUD"
  ],
  "MMR": [
    "MMK"
  ],
  "POL": [
    "PLN"
  ],
  "JOR": [
    "JOD"
  ],
  "HKG": [
    "HKD"
  ],
  "COD": [
    "CDF"
  ],
  "ERI": [
    "ERN"
  ],
  "KIR": [
    "AUD",
    "KID"
  ],
  "MHL": [
    "USD"
  ],
  "BFA": [
    "XOF"
  ],
  "ZWE": [
    "ZWL"
  ],
  "KEN": [
    "KES"
  ],
  "COM": [
    "KMF"
  ],
  "GIB": [
    "GIP"
  ],
  "BRN": [
    "BND",
    "SGD"
  ],
  "SWE": [
    "SEK"
  ],
  "LSO": [
    "LSL",
    "ZAR"
  ],
  "IMN": [
    "GBP",
    "IMP"
  ],
  "FSM": [
    "USD"
  ],
  "TZA": [
    "TZS"
  ],
  "CPV": [
    "CVE"
  ],
  "AFG": [
    "AFN"
  ],
  "AND": [
    "EUR"
  ],
  "GRC": [
    "EUR"
  ],
  "VNM": [
    "VND"
  ],
  "ATF": [
    "EUR"
  ],
  "IRQ": [
    "IQD"
  ],
  "LBY": [
    "LYD"
  ],
  "PRT": [
    "EUR"
  ],
  "PAK": [
    "PKR"
  ],
  "MDV": [
    "MVR"
  ],
  "MAR": [
    "MAD"
  ],
  "BIH": [
    "BAM"
  ],
  "WSM": [
    "WST"
  ],
  "PSE": [
    "EGP",
    "ILS",
    "JOD"
  ],
  "OMN": [
    "OMR"
  ],
  "BHR": [
    "BHD"
  ],
  "USA": [
    "USD"
  ],
  "PRI": [
    "USD"
  ],
  "IOT": [
    "USD"
  ],
  "JEY": [
    "GBP",
    "JEP"
  ],
  "MKD": [
    "MKD"
  ],
  "TUN": [
    "TND"
  ],
  "TTO": [
    "TTD"
  ],
  "EST": [
    "EUR"
  ],
  "SGP": [
    "SGD"
  ],
  "PAN": [
    "PAB",
    "USD"
  ],
  "CHE": [
    "CHF"
  ],
  "URY": [
    "UYU"
  ],
  "TJK": [
    "TJS"
  ],
  "TWN": [
    "TWD"
  ],
  "ZAF": [
    "ZAR"
  ],
  "LIE": [
    "CHF"
  ],
  "BRA": [
    "BRL"
  ],
  "ARM": [
    "AMD"
  ],
  "GEO": [
    "GEL"
  ],
  "ALA": [
    "EUR"
  ],
  "QAT": [
    "QAR"
  ],
  "DMA": [
    "XCD"
  ],
  "UKR": [
    "UAH"
  ],
  "GIN": [
    "GNF"
  ],
  "MAC": [
    "MOP"
  ],
  "ESH": [
    "DZD",
    "MAD",
    "MRU"
  ],
  "CZE": [
    "CZK"
  ],
  "AUT": [
    "EUR"
  ],
  "KNA": [
    "XCD"
  ],
  "LCA": [
    "XCD"
  ],
  "YEM": [
    "YER"
  ],
  "RWA": [
    "RWF"
  ],
  "MCO": [
    "EUR"
  ],
  "STP": [
    "STN"
  ],
  "COG": [
    "XAF"
  ],
  "PRY": [
    "PYG"
  ],
  "MOZ": [
    "MZN"
  ],
  "FRA": [
    "EUR"
  ],
  "SWZ": [
    "SZL",
    "ZAR"
  ],
  "BRB": [
    "BBD"
  ],
  "ESP": [
    "EUR"
  ],
  "THA": [
    "THB"
  ],
  "GNB": [
    "XOF"
  ],
  "AGO": [
    "AOA"
  ],
  "IND": [
    "INR"
  ],
  "MTQ": [
    "EUR"
  ],
  "NCL": [
    "XPF"
  ],
  "SYC": [
    "SCR"
  ],
  "FLK": [
    "FKP"
  ],
  "GBR": [
    "GBP"
  ],
  "FJI": [
    "FJD"
  ],
  "SMR": [
    "EUR"
  ],
  "MLI": [
    "XOF"
  ],
  "CAN": [
    "CAD"
  ],
  "JAM": [
    "JMD"
  ],
  "NRU": [
    "AUD"
  ],
  "IDN": [
    "IDR"
  ],
  "GUM": [
    "USD"
  ],
  "CIV": [
    "XOF"
  ],
  "KWT": [
    "KWD"
  ],
  "PHL": [
    "PHP"
  ],
  "GUY": [
    "GYD"
  ],
  "HUN": [
    "HUF"
  ],
  "MEX": [
    "MXN"
  ],
  "PRK": [
    "KPW"
  ],
  "ROU": [
    "RON"
  ],
  "SUR": [
    "SRD"
  ],
  "ASM": [
    "USD"
  ],
  "NPL": [
    "NPR"
  ],
  "TCD": [
    "XAF"
  ],
  "SRB": [
    "RSD"
  ],
  "KHM": [
    "KHR",
    "USD"
  ],
  "MYS": [
    "MYR"
  ],
  "CYP": [
    "EUR"
  ]
}